MANIFEST.in
setup.py
django_sslutils.egg-info/PKG-INFO
django_sslutils.egg-info/SOURCES.txt
django_sslutils.egg-info/dependency_links.txt
django_sslutils.egg-info/requires.txt
django_sslutils.egg-info/top_level.txt
sslutils/__init__.py
sslutils/conf.py
sslutils/decorators.py
sslutils/middleware.py
sslutils/models.py
sslutils/tests.py
sslutils/utils.py
sslutils/views.py