Metadata-Version: 1.1
Name: django-sslutils
Version: 0.1.1
Summary: SSL helpers for Django
Home-page: https://github.com/allanlei/django-sslutils
Author: Allan Lei
Author-email: allanlei@helveticode.com
License: UNKNOWN
Keywords: django ssl
Platform: UNKNOWN
Classifier: Development Status :: 4 - Beta
Classifier: Environment :: Web Environment
Classifier: Framework :: Django
Classifier: Intended Audience :: Developers
Classifier: License :: OSI Approved :: BSD License
Classifier: Operating System :: OS Independent
Classifier: Programming Language :: Python
Classifier: Topic :: Security
Classifier: Topic :: Internet :: WWW/HTTP
Classifier: Topic :: Software Development :: Libraries :: Python Modules
